Lab3/ex3/fulladder.v
module fulladder( sum, co, a, b, ci);

  input   a, b, ci;
  output  sum, co;

  // FILL HERE
  wire s1,c2,c3,c4;
  xor (s1,a,b); //s1 = a + b
  xor (sum, s1, ci); // sum = s1 + ci

  // find the carry by testing all the possible combinations of 2 input params - if one of the options is '1' - carry is '1'

  and(c1,a,ci);
  and(c2, b, ci);
  and(c3, a, b);
  or (co, c1, c2, c3);

endmodule

Lab3/ex4/add4.v
`include "../ex3/fulladder.v"
module  add4( sum, co, a, b, ci);

  input   [3:0] a, b;
  input   ci;
  output  [3:0] sum;
  output  co;

  // FILL HERE
  wire [2:0] carries; // save an array of carries from each fulladder operation
  //for each bit of the sum, we are adding the respective a+b bits
  // and including the carry from the previos bit
  fulladder adder1(sum[0], carries[0], a[0], b[0], ci);
  fulladder adder2(sum[1], carries[1], a[1], b[1], carries[0]);
  fulladder adder3(sum[2], carries[2], a[2], b[2], carries[1]);
  fulladder adder4(sum[3], co, a[3], b[3], carries[2]);
endmodule

Lab3/ex5/addsub.v
`include "../ex4/add4.v"
module	addsub( result, operand_a, operand_b, mode );

	input	[3:0]	operand_a, operand_b;
	input	mode;
	output	[3:0]	result;
	wire co;
	wire	[3:0]	xor_b;

	xor	g0(xor_b[0], mode, operand_b[0]);
	xor	g1(xor_b[1], mode, operand_b[1]);
	xor	g2(xor_b[2], mode, operand_b[2]);
	xor	g3(xor_b[3], mode, operand_b[3]);
	
	add4	m1(
		.sum(result),
		.co(co),
		.a(operand_a),	 
		.b(xor_b),	
		.ci(mode)
	);	
endmodule

Lab3/ex5/addsub_tb.v
`include "addsub.v"
module	addsub_tb;
	
	// for DUT port connection
	reg					mode;
	reg 	[3:0]	operand_a, operand_b;
	wire	[3:0] result;
	wire co;
	
	// for pattern generation
	integer			a, b, expect, error_num, t;
	reg					overflow;
	wire	[3:0]	expect_out = expect[3:0];	// compare "expect_out" with "result"

	addsub addsub(result, operand_a, operand_b, mode);

	// give stimulus pattern
	initial begin
	error_num = 0;

	$dumpfile("waves.vcd");
	$dumpvars;

	$display( "\nTest subtraction mode." );
	#10 mode = 1'b1;
	
	for( a=-8; a<=7; a=a+1 ) begin
		for( b=-8; b<=7; b=b+1 ) begin
			
			operand_a = a[3:0];
			operand_b = b[3:0];
			expect = a - b;
	
			#1;
			if( expect >= -8 && expect <= 7 ) begin
				overflow = 1'b0;
				if( expect[3:0] !== result ) begin
					error_num = error_num + 1;
					$display( "Error(%d):(%d)-(%d) Expect(%b) Output(%b)", error_num[9:0], a, b, expect[3:0], result );
				end
			end	else begin
				overflow = 1'b1;
			end
	
			#1;
		end
	end

	$display( "\nTest addition mode." );
	mode = 1'b0;
	
	for( a=-8; a<=7; a=a+1 ) begin
		for( b=-8; b<=7; b=b+1 ) begin
			
			operand_a = a[3:0];
			operand_b = b[3:0];
			expect = a + b;
	
			#1;
			if( expect >= -8 && expect <= 7 ) begin
				overflow = 1'b0;
				if( expect[3:0] !== result ) begin
					error_num = error_num + 1;
					$display( "Error(%d):(%d)+(%d) Expect(%b) Output(%b)", error_num[9:0], a, b, expect[3:0], result );
				end
			end	else begin
				overflow = 1'b1;
			end
	
			#1;
		end
	end
	
	if( error_num==0 )
		$display( "\nPass all test\n" );
	else
		$display( "\nFail, error number = %d\n", error_num );
	
	#10 $finish;
	end

endmodule

Lab3/ex5/waves.vcd
$date
	Mon Nov 15 17:17:09 2021
$end
$version
	Icarus Verilog
$end
$timescale
	1s
$end
$scope module addsub_tb $end
$var wire 4 ! result [3:0] $end
$var wire 4 " expect_out [3:0] $end
$var reg 1 # mode $end
$var reg 4 $ operand_a [3:0] $end
$var reg 4 % operand_b [3:0] $end
$var reg 1 & overflow $end
$var integer 32 ' a [31:0] $end
$var integer 32 ( b [31:0] $end
$var integer 32 ) error_num [31:0] $end
$var integer 32 * expect [31:0] $end
$scope module addsub $end
$var wire 1 # mode $end
$var wire 4 + operand_a [3:0] $end
$var wire 4 , operand_b [3:0] $end
$var wire 4 - xor_b [3:0] $end
$var wire 4 . result [3:0] $end
$var wire 1 / co $end
$scope module m1 $end
$var wire 4 0 a [3:0] $end
$var wire 4 1 b [3:0] $end
$var wire 1 # ci $end
$var wire 4 2 sum [3:0] $end
$var wire 1 / co $end
$var wire 3 3 carries [2:0] $end
$scope module adder1 $end
$var wire 1 4 a $end
$var wire 1 5 b $end
$var wire 1 6 c1 $end
$var wire 1 7 c2 $end
$var wire 1 8 c3 $end
$var wire 1 # ci $end
$var wire 1 9 co $end
$var wire 1 : s1 $end
$var wire 1 ; sum $end
$upscope $end
$scope module adder2 $end
$var wire 1 < a $end
$var wire 1 = b $end
$var wire 1 > c1 $end
$var wire 1 ? c2 $end
$var wire 1 @ c3 $end
$var wire 1 A ci $end
$var wire 1 B co $end
$var wire 1 C s1 $end
$var wire 1 D sum $end
$upscope $end
$scope module adder3 $end
$var wire 1 E a $end
$var wire 1 F b $end
$var wire 1 G c1 $end
$var wire 1 H c2 $end
$var wire 1 I c3 $end
$var wire 1 J ci $end
$var wire 1 K co $end
$var wire 1 L s1 $end
$var wire 1 M sum $end
$upscope $end
$scope module adder4 $end
$var wire 1 N a $end
$var wire 1 O b $end
$var wire 1 P c1 $end
$var wire 1 Q c2 $end
$var wire 1 R c3 $end
$var wire 1 S ci $end
$var wire 1 / co $end
$var wire 1 T s1 $end
$var wire 1 U sum $end
$upscope $end
$upscope $end
$upscope $end
$upscope $end
$enddefinitions $end
#0
$dumpvars
xU
xT
xS
xR
xQ
xP
xO
xN
xM
xL
xK
xJ
xI
xH
xG
xF
xE
xD
xC
xB
xA
x@
x?
x>
x=
x<
x;
x:
x9
x8
x7
x6
x5
x4
bx 3
bx 2
bx 1
bx 0
x/
bx .
bx -
bx ,
bx +
bx *
b0 )
bx (
bx '
x&
bx %
bx $
x#
bx "
bx !
$end
#10
1/
0U
1P
1S
1K
0M
1H
1J
1B
0D
1?
1A
b0 !
b0 .
b0 2
0;
b111 3
19
1:
17
1C
1L
1T
0Q
0R
15
1=
1F
0O
b111 -
b111 1
06
08
0>
0@
0G
0I
b0 "
04
0<
0E
1N
b0 *
b1000 %
b1000 ,
b1000 $
b1000 +
b1000 0
b11111111111111111111111111111000 (
b11111111111111111111111111111000 '
1#
#11
0&
#12
0/
1U
0P
0S
0K
1M
0H
0J
0B
1D
0?
0A
b1111 !
b1111 .
b1111 2
1;
b0 3
09
0:
07
05
b110 -
b110 1
b1111 "
b11111111111111111111111111111111 *
b1001 %
b1001 ,
b11111111111111111111111111111001 (
#14
1A
0;
b1 3
19
b1110 !
b1110 .
b1110 2
1D
1:
17
0C
15
0=
b101 -
b101 1
b1110 "
b11111111111111111111111111111110 *
b1010 %
b1010 ,
b11111111111111111111111111111010 (
#16
0D
0A
b1101 !
b1101 .
b1101 2
1;
b0 3
09
0:
07
05
b100 -
b100 1
b1101 "
b11111111111111111111111111111101 *
b1011 %
b1011 ,
b11111111111111111111111111111011 (
#18
1J
1B
1?
1A
0;
b11 3
19
0D
b1100 !
b1100 .
b1100 2
1M
1:
17
1C
0L
15
1=
0F
b11 -
b11 1
b1100 "
b11111111111111111111111111111100 *
b1100 %
b1100 ,
b11111111111111111111111111111100 (
#20
0M
0J
0B
1D
0?
0A
b1011 !
b1011 .
b1011 2
1;
b0 3
09
0:
07
05
b10 -
b10 1
b1011 "
b11111111111111111111111111111011 *
b1101 %
b1101 ,
b11111111111111111111111111111101 (
#22
1A
0;
b1 3
19
b1010 !
b1010 .
b1010 2
1D
1:
17
0C
15
0=
b1 -
b1 1
b1010 "
b11111111111111111111111111111010 *
b1110 %
b1110 ,
b11111111111111111111111111111110 (
#24
0D
0A
b1001 !
b1001 .
b1001 2
1;
b0 3
09
0:
07
05
b0 -
b0 1
b1001 "
b11111111111111111111111111111001 *
b1111 %
b1111 ,
b11111111111111111111111111111111 (
#26
1P
1Q
1S
1K
1H
1J
1B
1?
1A
0;
b111 3
19
0D
0M
b1000 !
b1000 .
b1000 2
1U
1/
1:
17
1C
1L
0T
1R
15
1=
1F
1O
b1111 -
b1111 1
b1000 "
b11111111111111111111111111111000 *
b0 %
b0 ,
b0 (
#28
0U
0P
0Q
0S
0K
1M
0H
0J
0B
1D
0?
0A
b111 !
b111 .
b111 2
1;
b0 3
09
0:
07
05
b1110 -
b1110 1
b111 "
b11111111111111111111111111110111 *
b1 %
b1 ,
b1 (
#29
1&
#30
1A
0;
b1 3
19
b110 !
b110 .
b110 2
1D
1:
17
0C
15
0=
b1101 -
b1101 1
b110 "
b11111111111111111111111111110110 *
b10 %
b10 ,
b10 (
#32
0D
0A
b101 !
b101 .
b101 2
1;
b0 3
09
0:
07
05
b1100 -
b1100 1
b101 "
b11111111111111111111111111110101 *
b11 %
b11 ,
b11 (
#34
1J
1B
1?
1A
0;
b11 3
19
0D
b100 !
b100 .
b100 2
1M
1:
17
1C
0L
15
1=
0F
b1011 -
b1011 1
b100 "
b11111111111111111111111111110100 *
b100 %
b100 ,
b100 (
#36
0M
0J
0B
1D
0?
0A
b11 !
b11 .
b11 2
1;
b0 3
09
0:
07
05
b1010 -
b1010 1
b11 "
b11111111111111111111111111110011 *
b101 %
b101 ,
b101 (
#38
1A
0;
b1 3
19
b10 !
b10 .
b10 2
1D
1:
17
0C
15
0=
b1001 -
b1001 1
b10 "
b11111111111111111111111111110010 *
b110 %
b110 ,
b110 (
#40
0D
0A
b1 !
b1 .
b1 2
1;
b0 3
09
0:
07
05
b1000 -
b1000 1
b1 "
b11111111111111111111111111110001 *
b111 %
b111 ,
b111 (
#42
1P
1S
1K
1H
1J
1B
0M
0U
1/
17
18
1C
1?
1L
1T
0R
1A
15
1=
1F
0O
b1 !
b1 .
b1 2
1;
b111 3
19
b111 -
b111 1
0:
16
14
b1 *
b1000 %
b1000 ,
b1001 $
b1001 +
b1001 0
b11111111111111111111111111111001 '
b11111111111111111111111111111000 (
#43
0&
#44
b0 !
b0 .
b0 2
0;
1:
07
08
05
b110 -
b110 1
b0 "
b0 *
b1001 %
b1001 ,
b11111111111111111111111111111001 (
#46
0/
1U
0P
0S
0K
1M
0H
0J
1;
b1111 !
b1111 .
b1111 2
1D
b1 3
0B
0:
17
18
0C
0?
15
0=
b101 -
b101 1
b1111 "
b11111111111111111111111111111111 *
b1010 %
b1010 ,
b11111111111111111111111111111010 (
#48
b1110 !
b1110 .
b1110 2
0;
1:
07
08
05
b100 -
b100 1
b1110 "
b11111111111111111111111111111110 *
b1011 %
b1011 ,
b11111111111111111111111111111011 (
#50
1J
1;
0D
b11 3
1B
b1101 !
b1101 .
b1101 2
1M
0:
17
18
1C
1?
0L
15
1=
0F
b11 -
b11 1
b1101 "
b11111111111111111111111111111101 *
b1100 %
b1100 ,
b11111111111111111111111111111100 (
#52
b1100 !
b1100 .
b1100 2
0;
1:
07
08
05
b10 -
b10 1
b1100 "
b11111111111111111111111111111100 *
b1101 %
b1101 ,
b11111111111111111111111111111101 (
#54
0M
0J
1;
b1011 !
b1011 .
b1011 2
1D
b1 3
0B
0:
17
18
0C
0?
15
0=
b1 -
b1 1
b1011 "
b11111111111111111111111111111011 *
b1110 %
b1110 ,
b11111111111111111111111111111110 (
#56
b1010 !
b1010 .
b1010 2
0;
1:
07
08
05
b0 -
b0 1
b1010 "
b11111111111111111111111111111010 *
b1111 %
b1111 ,
b11111111111111111111111111111111 (
#58
1P
1Q
1S
1K
1H
1J
1;
0D
b111 3
1B
0M
b1001 !
b1001 .
b1001 2
1U
1/
0:
17
18
1C
1?
1L
0T
1R
15
1=
1F
1O
b1111 -
b1111 1
b1001 "
b11111111111111111111111111111001 *
b0 %
b0 ,
b0 (
#60
b1000 !
b1000 .
b1000 2
0;
1:
07
08
05
b1110 -
b1110 1
b1000 "
b11111111111111111111111111111000 *
b1 %
b1 ,
b1 (
#62
0U
0P
0Q
0S
0K
1M
0H
0J
1;
b111 !
b111 .
b111 2
1D
b1 3
0B
0:
17
18
0C
0?
15
0=
b1101 -
b1101 1
b111 "
b11111111111111111111111111110111 *
b10 %
b10 ,
b10 (
#63
1&
#64
b110 !
b110 .
b110 2
0;
1:
07
08
05
b1100 -
b1100 1
b110 "
b11111111111111111111111111110110 *
b11 %
b11 ,
b11 (
#66
1J
1;
0D
b11 3
1B
b101 !
b101 .
b101 2
1M
0:
17
18
1C
1?
0L
15
1=
0F
b1011 -
b1011 1
b101 "
b11111111111111111111111111110101 *
b100 %
b100 ,
b100 (
#68
b100 !
b100 .
b100 2
0;
1:
07
08
05
b1010 -
b1010 1
b100 "
b11111111111111111111111111110100 *
b101 %
b101 ,
b101 (
#70
0M
0J
1;
b11 !
b11 .
b11 2
1D
b1 3
0B
0:
17
18
0C
0?
15
0=
b1001 -
b1001 1
b11 "
b11111111111111111111111111110011 *
b110 %
b110 ,
b110 (
#72
b10 !
b10 .
b10 2
0;
1:
07
08
05
b1000 -
b1000 1
b10 "
b11111111111111111111111111110010 *
b111 %
b111 ,
b111 (
#74
1?
1P
1S
1K
0U
1/
17
1@
1L
1H
1T
0R
1A
1J
15
1=
1F
0O
0;
19
b10 !
b10 .
b10 2
1D
b111 3
1B
b111 -
b111 1
1:
06
0C
1>
04
1<
b10 *
b1000 %
b1000 ,
b1010 $
b1010 +
b1010 0
b11111111111111111111111111111010 '
b11111111111111111111111111111000 (
#75
0&
#76
0D
0>
0?
0A
b1 !
b1 .
b1 2
1;
b110 3
09
0:
07
05
b110 -
b110 1
b1 "
b1 *
b1001 %
b1001 ,
b11111111111111111111111111111001 (
#78
1/
0U
1P
1S
1K
1>
0M
1H
1A
1J
0;
19
b0 !
b0 .
b0 2
0D
b111 3
1B
1:
17
1C
0@
15
0=
b101 -
b101 1
b0 "
b0 *
b1010 %
b1010 ,
b11111111111111111111111111111010 (
#80
0/
1U
0P
0S
0K
1M
0H
0J
0B
1D
0>
0A
b1111 !
b1111 .
b1111 2
1;
b0 3
09
0:
07
05
b100 -
b100 1
b1111 "
b11111111111111111111111111111111 *
b1011 %
b1011 ,
b11111111111111111111111111111011 (
#82
1>
1?
1A
1J
0;
19
1D
b11 3
1B
b1110 !
b1110 .
b1110 2
1M
1:
17
0C
1@
0L
15
1=
0F
b11 -
b11 1
b1110 "
b11111111111111111111111111111110 *
b1100 %
b1100 ,
b11111111111111111111111111111100 (
#84
0D
0>
0?
0A
b1101 !
b1101 .
b1101 2
1;
b10 3
09
0:
07
05
b10 -
b10 1
b1101 "
b11111111111111111111111111111101 *
b1101 %
b1101 ,
b11111111111111111111111111111101 (
#86
1>
1M
1A
1J
0;
19
b1100 !
b1100 .
b1100 2
0D
b11 3
1B
1:
17
1C
0@
15
0=
b1 -
b1 1
b1100 "
b11111111111111111111111111111100 *
b1110 %
b1110 ,
b11111111111111111111111111111110 (
#88
0M
0J
0B
1D
0>
0A
b1011 !
b1011 .
b1011 2
1;
b0 3
09
0:
07
05
b0 -
b0 1
b1011 "
b11111111111111111111111111111011 *
b1111 %
b1111 ,
b11111111111111111111111111111111 (
#90
1P
1Q
1S
1K
1>
1?
1H
1A
1J
0;
19
1D
b111 3
1B
0M
b1010 !
b1010 .
b1010 2
1U
1/
1:
17
0C
1@
1L
0T
1R
15
1=
1F
1O
b1111 -
b1111 1
b1010 "
b11111111111111111111111111111010 *
b0 %
b0 ,
b0 (
#92
0D
0>
0?
0A
b1001 !
b1001 .
b1001 2
1;
b110 3
09
0:
07
05
b1110 -
b1110 1
b1001 "
b11111111111111111111111111111001 *
b1 %
b1 ,
b1 (
#94
1U
1P
1Q
1S
1K
1>
0M
1H
1A
1J
0;
19
b1000 !
b1000 .
b1000 2
0D
b111 3
1B
1:
17
1C
0@
15
0=
b1101 -
b1101 1
b1000 "
b11111111111111111111111111111000 *
b10 %
b10 ,
b10 (
#96
0U
0P
0Q
0S
0K
1M
0H
0J
0B
1D
0>
0A
b111 !
b111 .
b111 2
1;
b0 3
09
0:
07
05
b1100 -
b1100 1
b111 "
b11111111111111111111111111110111 *
b11 %
b11 ,
b11 (
#97
1&
#98
1>
1?
1A
1J
0;
19
1D
b11 3
1B
b110 !
b110 .
b110 2
1M
1:
17
0C
1@
0L
15
1=
0F
b1011 -
b1011 1
b110 "
b11111111111111111111111111110110 *
b100 %
b100 ,
b100 (
#100
0D
0>
0?
0A
b101 !
b101 .
b101 2
1;
b10 3
09
0:
07
05
b1010 -
b1010 1
b101 "
b11111111111111111111111111110101 *
b101 %
b101 ,
b101 (
#102
1>
1M
1A
1J
0;
19
b100 !
b100 .
b100 2
0D
b11 3
1B
1:
17
1C
0@
15
0=
b1001 -
b1001 1
b100 "
b11111111111111111111111111110100 *
b110 %
b110 ,
b110 (
#104
0M
0J
0B
1D
0>
0A
b11 !
b11 .
b11 2
1;
b0 3
09
0:
07
05
b1000 -
b1000 1
b11 "
b11111111111111111111111111110011 *
b111 %
b111 ,
b111 (
#106
1P
1S
1K
1H
1J
1B
0M
0U
1/
1>
17
18
0C
1?
1@
1L
1T
0R
1A
15
1=
1F
0O
b11 !
b11 .
b11 2
1;
b111 3
19
b111 -
b111 1
0:
16
14
b11 *
b1000 %
b1000 ,
b1011 $
b1011 +
b1011 0
b11111111111111111111111111111011 '
b11111111111111111111111111111000 (
#107
0&
#108
b10 !
b10 .
b10 2
0;
1:
07
08
05
b110 -
b110 1
b10 "
b10 *
b1001 %
b1001 ,
b11111111111111111111111111111001 (
#110
1;
b1 !
b1 .
b1 2
0D
0:
17
18
1C
0?
0@
15
0=
b101 -
b101 1
b1 "
b1 *
b1010 %
b1010 ,
b11111111111111111111111111111010 (
#112
b0 !
b0 .
b0 2
0;
1:
07
08
05
b100 -
b100 1
b0 "
b0 *
b1011 %
b1011 ,
b11111111111111111111111111111011 (
#114
0/
1U
0P
0S
1;
1D
b1111 !
b1111 .
b1111 2
1M
b11 3
0K
0:
17
18
0C
1?
1@
0L
0H
15
1=
0F
b11 -
b11 1
b1111 "
b11111111111111111111111111111111 *
b1100 %
b1100 ,
b11111111111111111111111111111100 (
#116
b1110 !
b1110 .
b1110 2
0;
1:
07
08
05
b10 -
b10 1
b1110 "
b11111111111111111111111111111110 *
b1101 %
b1101 ,
b11111111111111111111111111111101 (
#118
1;
b1101 !
b1101 .
b1101 2
0D
0:
17
18
1C
0?
0@
15
0=
b1 -
b1 1
b1101 "
b11111111111111111111111111111101 *
b1110 %
b1110 ,
b11111111111111111111111111111110 (
#120
b1100 !
b1100 .
b1100 2
0;
1:
07
08
05
b0 -
b0 1
b1100 "
b11111111111111111111111111111100 *
b1111 %
b1111 ,
b11111111111111111111111111111111 (
#122
1P
1Q
1S
1;
1D
0M
b111 3
1K
b1011 !
b1011 .
b1011 2
1U
1/
0:
17
18
0C
1?
1@
1L
1H
0T
1R
15
1=
1F
1O
b1111 -
b1111 1
b1011 "
b11111111111111111111111111111011 *
b0 %
b0 ,
b0 (
#124
b1010 !
b1010 .
b1010 2
0;
1:
07
08
05
b1110 -
b1110 1
b1010 "
b11111111111111111111111111111010 *
b1 %
b1 ,
b1 (
#126
1;
b1001 !
b1001 .
b1001 2
0D
0:
17
18
1C
0?
0@
15
0=
b1101 -
b1101 1
b1001 "
b11111111111111111111111111111001 *
b10 %
b10 ,
b10 (
#128
b1000 !
b1000 .
b1000 2
0;
1:
07
08
05
b1100 -
b1100 1
b1000 "
b11111111111111111111111111111000 *
b11 %
b11 ,
b11 (
#130
0U
0P
0Q
0S
1;
1D
b111 !
b111 .
b111 2
1M
b11 3
0K
0:
17
18
0C
1?
1@
0L
0H
15
1=
0F
b1011 -
b1011 1
b111 "
b11111111111111111111111111110111 *
b100 %
b100 ,
b100 (
#131
1&
#132
b110 !
b110 .
b110 2
0;
1:
07
08
05
b1010 -
b1010 1
b110 "
b11111111111111111111111111110110 *
b101 %
b101 ,
b101 (
#134
1;
b101 !
b101 .
b101 2
0D
0:
17
18
1C
0?
0@
15
0=
b1001 -
b1001 1
b101 "
b11111111111111111111111111110101 *
b110 %
b110 ,
b110 (
#136
b100 !
b100 .
b100 2
0;
1:
07
08
05
b1000 -
b1000 1
b100 "
b11111111111111111111111111110100 *
b111 %
b111 ,
b111 (
#138
1H
1?
1P
17
1I
1T
0R
1A
1J
1S
15
1=
1F
0O
0;
19
0D
1B
b100 !
b100 .
b100 2
1M
b111 3
1K
b111 -
b111 1
1:
06
1C
0>
0L
1G
04
0<
1E
b100 *
b1000 %
b1000 ,
b1100 $
b1100 +
b1100 0
b11111111111111111111111111111100 '
b11111111111111111111111111111000 (
#139
0&
#140
0M
0G
0H
0J
0B
1D
0?
0A
b11 !
b11 .
b11 2
1;
b100 3
09
0:
07
05
b110 -
b110 1
b11 "
b11 *
b1001 %
b1001 ,
b11111111111111111111111111111001 (
#142
1A
0;
b101 3
19
b10 !
b10 .
b10 2
1D
1:
17
0C
15
0=
b101 -
b101 1
b10 "
b10 *
b1010 %
b1010 ,
b11111111111111111111111111111010 (
#144
0D
0A
b1 !
b1 .
b1 2
1;
b100 3
09
0:
07
05
b100 -
b100 1
b1 "
b1 *
b1011 %
b1011 ,
b11111111111111111111111111111011 (
#146
1G
1J
1B
1/
1?
0U
1P
1A
1S
0;
19
0D
b0 !
b0 .
b0 2
0M
b111 3
1K
1:
17
1C
1L
0I
15
1=
0F
b11 -
b11 1
b0 "
b0 *
b1100 %
b1100 ,
b11111111111111111111111111111100 (
#148
0/
1U
0P
0S
0K
1M
0G
0J
0B
1D
0?
0A
b1111 !
b1111 .
b1111 2
1;
b0 3
09
0:
07
05
b10 -
b10 1
b1111 "
b11111111111111111111111111111111 *
b1101 %
b1101 ,
b11111111111111111111111111111101 (
#150
1A
0;
b1 3
19
b1110 !
b1110 .
b1110 2
1D
1:
17
0C
15
0=
b1 -
b1 1
b1110 "
b11111111111111111111111111111110 *
b1110 %
b1110 ,
b11111111111111111111111111111110 (
#152
0D
0A
b1101 !
b1101 .
b1101 2
1;
b0 3
09
0:
07
05
b0 -
b0 1
b1101 "
b11111111111111111111111111111101 *
b1111 %
b1111 ,
b11111111111111111111111111111111 (
#154
1G
1H
1J
1B
1?
1P
1Q
1A
1S
0;
19
0D
1M
b111 3
1K
b1100 !
b1100 .
b1100 2
1U
1/
1:
17
1C
0L
1I
0T
1R
15
1=
1F
1O
b1111 -
b1111 1
b1100 "
b11111111111111111111111111111100 *
b0 %
b0 ,
b0 (
#156
0M
0G
0H
0J
0B
1D
0?
0A
b1011 !
b1011 .
b1011 2
1;
b100 3
09
0:
07
05
b1110 -
b1110 1
b1011 "
b11111111111111111111111111111011 *
b1 %
b1 ,
b1 (
#158
1A
0;
b101 3
19
b1010 !
b1010 .
b1010 2
1D
1:
17
0C
15
0=
b1101 -
b1101 1
b1010 "
b11111111111111111111111111111010 *
b10 %
b10 ,
b10 (
#160
0D
0A
b1001 !
b1001 .
b1001 2
1;
b100 3
09
0:
07
05
b1100 -
b1100 1
b1001 "
b11111111111111111111111111111001 *
b11 %
b11 ,
b11 (
#162
1G
1J
1B
1?
1U
1P
1Q
1A
1S
0;
19
0D
b1000 !
b1000 .
b1000 2
0M
b111 3
1K
1:
17
1C
1L
0I
15
1=
0F
b1011 -
b1011 1
b1000 "
b11111111111111111111111111111000 *
b100 %
b100 ,
b100 (
#164
0U
0P
0Q
0S
0K
1M
0G
0J
0B
1D
0?
0A
b111 !
b111 .
b111 2
1;
b0 3
09
0:
07
05
b1010 -
b1010 1
b111 "
b11111111111111111111111111110111 *
b101 %
b101 ,
b101 (
#165
1&
#166
1A
0;
b1 3
19
b110 !
b110 .
b110 2
1D
1:
17
0C
15
0=
b1001 -
b1001 1
b110 "
b11111111111111111111111111110110 *
b110 %
b110 ,
b110 (
#168
0D
0A
b101 !
b101 .
b101 2
1;
b0 3
09
0:
07
05
b1000 -
b1000 1
b101 "
b11111111111111111111111111110101 *
b111 %
b111 ,
b111 (
#170
1G
1H
1P
1J
1S
1B
1M
1K
0U
1/
17
18
1C
1?
0L
1I
1T
0R
1A
15
1=
1F
0O
b101 !
b101 .
b101 2
1;
b111 3
19
b111 -
b111 1
0:
16
14
b101 *
b1000 %
b1000 ,
b1101 $
b1101 +
b1101 0
b11111111111111111111111111111101 '
b11111111111111111111111111111000 (
#171
0&
#172
b100 !
b100 .
b100 2
0;
1:
07
08
05
b110 -
b110 1
b100 "
b100 *
b1001 %
b1001 ,
b11111111111111111111111111111001 (
#174
0M
0G
0H
0J
1;
b11 !
b11 .
b11 2
1D
b101 3
0B
0:
17
18
0C
0?
15
0=
b101 -
b101 1
b11 "
b11 *
b1010 %
b1010 ,
b11111111111111111111111111111010 (
#176
b10 !
b10 .
b10 2
0;
1:
07
08
05
b100 -
b100 1
b10 "
b10 *
b1011 %
b1011 ,
b11111111111111111111111111111011 (
#178
1/
1G
0U
1P
1J
1S
1;
0D
1B
b1 !
b1 .
b1 2
0M
b111 3
1K
0:
17
18
1C
1?
1L
0I
15
1=
0F
b11 -
b11 1
b1 "
b1 *
b1100 %
b1100 ,
b11111111111111111111111111111100 (
#180
b0 !
b0 .
b0 2
0;
1:
07
08
05
b10 -
b10 1
b0 "
b0 *
b1101 %
b1101 ,
b11111111111111111111111111111101 (
#182
0/
1U
0P
0S
0K
1M
0G
0J
1;
b1111 !
b1111 .
b1111 2
1D
b1 3
0B
0:
17
18
0C
0?
15
0=
b1 -
b1 1
b1111 "
b11111111111111111111111111111111 *
b1110 %
b1110 ,
b11111111111111111111111111111110 (
#184
b1110 !
b1110 .
b1110 2
0;
1:
07
08
05
b0 -
b0 1
b1110 "
b11111111111111111111111111111110 *
b1111 %
b1111 ,
b11111111111111111111111111111111 (
#186
1G
1H
1P
1Q
1J
1S
1;
0D
1B
1M
b111 3
1K
b1101 !
b1101 .
b1101 2
1U
1/
0:
17
18
1C
1?
0L
1I
0T
1R
15
1=
1F
1O
b1111 -
b1111 1
b1101 "
b11111111111111111111111111111101 *
b0 %
b0 ,
b0 (
#188
b1100 !
b1100 .
b1100 2
0;
1:
07
08
05
b1110 -
b1110 1
b1100 "
b11111111111111111111111111111100 *
b1 %
b1 ,
b1 (
#190
0M
0G
0H
0J
1;
b1011 !
b1011 .
b1011 2
1D
b101 3
0B
0:
17
18
0C
0?
15
0=
b1101 -
b1101 1
b1011 "
b11111111111111111111111111111011 *
b10 %
b10 ,
b10 (
#192
b1010 !
b1010 .
b1010 2
0;
1:
07
08
05
b1100 -
b1100 1
b1010 "
b11111111111111111111111111111010 *
b11 %
b11 ,
b11 (
#194
1G
1U
1P
1Q
1J
1S
1;
0D
1B
b1001 !
b1001 .
b1001 2
0M
b111 3
1K
0:
17
18
1C
1?
1L
0I
15
1=
0F
b1011 -
b1011 1
b1001 "
b11111111111111111111111111111001 *
b100 %
b100 ,
b100 (
#196
b1000 !
b1000 .
b1000 2
0;
1:
07
08
05
b1010 -
b1010 1
b1000 "
b11111111111111111111111111111000 *
b101 %
b101 ,
b101 (
#198
0U
0P
0Q
0S
0K
1M
0G
0J
1;
b111 !
b111 .
b111 2
1D
b1 3
0B
0:
17
18
0C
0?
15
0=
b1001 -
b1001 1
b111 "
b11111111111111111111111111110111 *
b110 %
b110 ,
b110 (
#199
1&
#200
b110 !
b110 .
b110 2
0;
1:
07
08
05
b1000 -
b1000 1
b110 "
b11111111111111111111111111110110 *
b111 %
b111 ,
b111 (
#202
1?
1P
1S
1K
0U
1/
1G
17
1@
0L
1H
1I
1T
0R
1A
1J
15
1=
1F
0O
0;
19
b110 !
b110 .
b110 2
1D
b111 3
1B
b111 -
b111 1
1:
06
0C
1>
04
1<
b110 *
b1000 %
b1000 ,
b1110 $
b1110 +
b1110 0
b11111111111111111111111111111110 '
b11111111111111111111111111111000 (
#203
0&
#204
0D
0>
0?
0A
b101 !
b101 .
b101 2
1;
b110 3
09
0:
07
05
b110 -
b110 1
b101 "
b101 *
b1001 %
b1001 ,
b11111111111111111111111111111001 (
#206
1>
1M
1G
1H
1A
1J
0;
19
b100 !
b100 .
b100 2
0D
b111 3
1B
1:
17
1C
0@
15
0=
b101 -
b101 1
b100 "
b100 *
b1010 %
b1010 ,
b11111111111111111111111111111010 (
#208
0M
0G
0H
0J
0B
1D
0>
0A
b11 !
b11 .
b11 2
1;
b100 3
09
0:
07
05
b100 -
b100 1
b11 "
b11 *
b1011 %
b1011 ,
b11111111111111111111111111111011 (
#210
1/
1>
1?
1G
0U
1P
1A
1J
1S
0;
19
1D
1B
b10 !
b10 .
b10 2
0M
b111 3
1K
1:
17
0C
1@
1L
0I
15
1=
0F
b11 -
b11 1
b10 "
b10 *
b1100 %
b1100 ,
b11111111111111111111111111111100 (
#212
0D
0>
0?
0A
b1 !
b1 .
b1 2
1;
b110 3
09
0:
07
05
b10 -
b10 1
b1 "
b1 *
b1101 %
b1101 ,
b11111111111111111111111111111101 (
#214
1/
0U
1P
1S
1K
1>
0M
1G
1A
1J
0;
19
b0 !
b0 .
b0 2
0D
b111 3
1B
1:
17
1C
0@
15
0=
b1 -
b1 1
b0 "
b0 *
b1110 %
b1110 ,
b11111111111111111111111111111110 (
#216
0/
1U
0P
0S
0K
1M
0G
0J
0B
1D
0>
0A
b1111 !
b1111 .
b1111 2
1;
b0 3
09
0:
07
05
b0 -
b0 1
b1111 "
b11111111111111111111111111111111 *
b1111 %
b1111 ,
b11111111111111111111111111111111 (
#218
1>
1?
1G
1H
1P
1Q
1A
1J
1S
0;
19
1D
1B
1M
b111 3
1K
b1110 !
b1110 .
b1110 2
1U
1/
1:
17
0C
1@
0L
1I
0T
1R
15
1=
1F
1O
b1111 -
b1111 1
b1110 "
b11111111111111111111111111111110 *
b0 %
b0 ,
b0 (
#220
0D
0>
0?
0A
b1101 !
b1101 .
b1101 2
1;
b110 3
09
0:
07
05
b1110 -
b1110 1
b1101 "
b11111111111111111111111111111101 *
b1 %
b1 ,
b1 (
