Lab3/ex3/fulladder.v
module fulladder( sum, co, a, b, ci);

  input   a, b, ci;
  output  sum, co;

  // FILL HERE
  wire s1,c2,c3,c4;
  xor (s1,a,b); //s1 = a + b
  xor (sum, s1, ci); // sum = s1 + ci

  // find the carry by testing all the possible combinations of 2 input params - if one of the options is '1' - carry is '1'

  and(c1,a,ci);
  and(c2, b, ci);
  and(c3, a, b);
  or (co, c1, c2, c3);

endmodule

Lab3/ex4/add4.v
`include "../ex3/fulladder.v"
module  add4( sum, co, a, b, ci);

  input   [3:0] a, b;
  input   ci;
  output  [3:0] sum;
  output  co;

  // FILL HERE
  wire [2:0] carries; // save an array of carries from each fulladder operation
  //for each bit of the sum, we are adding the respective a+b bits
  // and including the carry from the previos bit
  fulladder adder1(sum[0], carries[0], a[0], b[0], ci);
  fulladder adder2(sum[1], carries[1], a[1], b[1], carries[0]);
  fulladder adder3(sum[2], carries[2], a[2], b[2], carries[1]);
  fulladder adder4(sum[3], co, a[3], b[3], carries[2]);
endmodule

Lab3/ex5/addsub.v
`include "../ex4/add4.v"
module	addsub( result, operand_a, operand_b, mode );

	input	[3:0]	operand_a, operand_b;
	input	mode;
	output	[3:0]	result;
	wire co;
	wire	[3:0]	xor_b;

	xor	g0(xor_b[0], mode, operand_b[0]);
	xor	g1(xor_b[1], mode, operand_b[1]);
	xor	g2(xor_b[2], mode, operand_b[2]);
	xor	g3(xor_b[3], mode, operand_b[3]);
	
	add4	m1(
		.sum(result),
		.co(co),
		.a(operand_a),	 
		.b(xor_b),	
		.ci(mode)
	);	
endmodule

Lab3/ex7/sat_count.v
`include "../ex5/addsub.v"

module sat_count(clk, reset, branch, taken, prediction);
   parameter N=2;
   input clk, reset, branch, taken;
   output prediction;

   // FILL HERE

   reg   [3:0] counter;
   reg   [3:0] e = {N{1'b1}} ;
   wire signed   [3:0] nxt_counter  ; 
   reg p ;

   addsub addsub(nxt_counter, counter, 4'b1, ~taken) ; // sets next counter to be ++ / -- depends on taken 
   
   always @(posedge clk)
      begin
      if (reset)  // on reset = 1 we init the counter
      counter <= 4'd0;
      else
         begin

            if(branch)
               begin

                  if(taken)
                     begin
                        if(nxt_counter > e )
                           counter <= e ; 
                        else 
                           counter <= nxt_counter;
                     end    
                  else  // taken = 0 
                     begin
                        if(nxt_counter < 0 )
                           counter <= 4'd0 ;
                        else 
                           counter <= nxt_counter ;
                     end
               end
            else 
               counter <= counter ; 
         end
         if(counter >= (2**(N-1)))
            assign p = 1 ;
         else
            assign p = 0 ;
      end
   
   assign prediction = p ;
   

endmodule

Lab3/ex7/sat_count_tb.v
`include "sat_count.v"

module main ;

reg clk, reset, branch, taken , answer;
wire prediction;

sat_count counter(clk, reset, branch, taken, prediction) ;

always #5 clk = ~clk; //taken from previous tb 

initial
     begin
        $display("starting 4 tests ");
        $dumpfile("waves.vcd");
        $dumpvars;
        clk = 0; 

        // TEST 1 
        taken = 0 ; 
        branch = 0 ; 
        reset = 1 ; 
        # 10;
        reset = 0 ; 

        if( prediction == 0)
            $display("First test passed");
        
        #10 ;

        // TEST 2 
        branch = 1;
        taken = 1 ;
        answer = 1; 
        #20 //after 2 cycles prediction should be 0
        answer = answer & (~prediction) ;
        #20 //after 2 cycles prediction should be 1
        answer = answer & (prediction) ;
        if ( answer)
            $display("Second test passed");
        #10 ;

        //TEST 3 

        taken = 0; 
        #40 // after 4 cycles should return 0 again
        if( prediction == 0)
            $display("Third test passed");
        
        #10 ;

        //TEST 4 

        branch = 0 ; 
        #20 // after 2 cycles shouldnt change 
        if( prediction == 0)
            $display("Fourth test passed");
        
        #10 ;

        $finish;
     end
endmodule

Lab3/ex7/waves.vcd
$date
	Fri Nov 19 13:28:15 2021
$end
$version
	Icarus Verilog
$end
$timescale
	1s
$end
$scope module main $end
$var wire 1 ! prediction $end
$var reg 1 " answer $end
$var reg 1 # branch $end
$var reg 1 $ clk $end
$var reg 1 % reset $end
$var reg 1 & taken $end
$scope module counter $end
$var wire 1 # branch $end
$var wire 1 $ clk $end
$var wire 1 ! prediction $end
$var wire 1 % reset $end
$var wire 1 & taken $end
$var wire 4 ' nxt_counter [3:0] $end
$var reg 4 ( counter [3:0] $end
$var reg 4 ) e [3:0] $end
$var reg 1 * p $end
$scope module addsub $end
$var wire 1 + mode $end
$var wire 4 , operand_a [3:0] $end
$var wire 4 - operand_b [3:0] $end
$var wire 4 . xor_b [3:0] $end
$var wire 4 / result [3:0] $end
$var wire 1 0 co $end
$scope module m1 $end
$var wire 4 1 a [3:0] $end
$var wire 4 2 b [3:0] $end
$var wire 1 + ci $end
$var wire 4 3 sum [3:0] $end
$var wire 1 0 co $end
$var wire 3 4 carries [2:0] $end
$scope module adder1 $end
$var wire 1 5 a $end
$var wire 1 6 b $end
$var wire 1 7 c1 $end
$var wire 1 8 c2 $end
$var wire 1 9 c3 $end
$var wire 1 + ci $end
$var wire 1 : co $end
$var wire 1 ; s1 $end
$var wire 1 < sum $end
$upscope $end
$scope module adder2 $end
$var wire 1 = a $end
$var wire 1 > b $end
$var wire 1 ? c1 $end
$var wire 1 @ c2 $end
$var wire 1 A c3 $end
$var wire 1 B ci $end
$var wire 1 C co $end
$var wire 1 D s1 $end
$var wire 1 E sum $end
$upscope $end
$scope module adder3 $end
$var wire 1 F a $end
$var wire 1 G b $end
$var wire 1 H c1 $end
$var wire 1 I c2 $end
$var wire 1 J c3 $end
$var wire 1 K ci $end
$var wire 1 L co $end
$var wire 1 M s1 $end
$var wire 1 N sum $end
$upscope $end
$scope module adder4 $end
$var wire 1 O a $end
$var wire 1 P b $end
$var wire 1 Q c1 $end
$var wire 1 R c2 $end
$var wire 1 S c3 $end
$var wire 1 T ci $end
$var wire 1 0 co $end
$var wire 1 U s1 $end
$var wire 1 V sum $end
$upscope $end
$upscope $end
$upscope $end
$upscope $end
$upscope $end
$enddefinitions $end
#0
$dumpvars
xV
xU
xT
xS
xR
xQ
1P
xO
xN
xM
xL
xK
xJ
xI
xH
1G
xF
xE
xD
xC
xB
xA
x@
x?
1>
x=
x<
x;
x:
09
08
x7
06
x5
bx 4
bx 3
b1110 2
bx 1
x0
bx /
b1110 .
b1 -
bx ,
1+
x*
b11 )
bx (
bx '
0&
1%
0$
0#
x"
x!
$end
#5
00
1V
0R
0T
0L
1N
0I
0K
0C
1E
0@
0B
b1111 '
b1111 /
b1111 3
1<
b0 4
0:
0;
07
1D
0?
0A
1M
0H
0J
1U
0Q
0S
05
0=
0F
0O
b0 (
b0 ,
b0 1
0!
0*
1$
#10
0$
0%
#15
1$
#20
0E
0N
0V
1;
0D
0M
0U
16
0>
0G
0P
b1 .
b1 2
b1 '
b1 /
b1 3
1<
0+
0$
1"
1&
1#
#25
1E
1B
b10 '
b10 /
b10 3
0<
b1 4
1:
0;
19
15
b1 (
b1 ,
b1 1
1$
#30
0$
#35
0N
0B
0K
1<
0:
b11 '
b11 /
b11 3
1E
b0 4
0C
1;
09
1D
0?
05
1=
b10 (
b10 ,
b10 1
1$
#40
0$
#45
1N
1K
1C
0E
1?
1B
b100 '
b100 /
b100 3
0<
b11 4
1:
0;
19
15
b11 (
b11 ,
b11 1
1!
1*
1$
#50
0$
#55
1$
#60
0$
#65
1$
#70
10
1R
1T
1E
0N
b111 4
1L
0V
1;
09
0D
1@
1A
1M
1I
1U
06
1>
1G
1P
b1110 .
b1110 2
b10 '
b10 /
b10 3
0<
17
08
1+
0$
0&
#75
0E
0?
0@
0B
b1 '
b1 /
b1 3
1<
b110 4
0:
0;
07
05
b10 (
b10 ,
b10 1
1$
#80
0$
#85
10
0V
1R
1T
1L
1@
0N
1I
1B
1K
0<
1:
b0 '
b0 /
b0 3
0E
b111 4
1C
1;
17
1D
0A
15
0=
b1 (
b1 ,
b1 1
1$
#90
0$
#95
00
1V
0R
0T
0L
1N
0I
0K
0C
1E
0@
0B
b1111 '
b1111 /
b1111 3
1<
b0 4
0:
0;
07
05
b0 (
b0 ,
b0 1
0!
0*
1$
#100
0$
#105
1$
#110
0$
#115
1$
#120
0$
0#
