Lab4/sram.v
/*****************************************
 * SRAM module: synchronus SRAM, 65536x16
 * 
 * inputs:
 * 
 * clk: system clock
 * addr[15:0]: 16 bit address
 * di[31:0]: 32 bit input data
 * en: enable signal
 * we: write enable (1 write, 0 read)
 ****************************************/
module SRAM(clk, addr, di, en, we, do);

   input clk;
   input [15:0] addr;
   input [31:0] di;
   input 	en;
   input 	we;

   output [31:0] do;
   
   reg [31:0] 	 do;
   reg [31:0] 	 mem[0:65535];
   
   always @(posedge clk)
     begin
	if (en) begin
	   if (we) begin
	      /***********************************
               * TODO: fill here
               **********************************/
	      $display("time %0d: write %08x -> mem[%04x]", $time, di, addr);
	   end
	   else begin
	      /***********************************
               * TODO: fill here
               **********************************/
	      $display("time %0d: read mem[%04x] -> %08x", $time, addr, mem[addr]);
	   end
	end
     end
endmodule // sram

Lab4/without_dma/defines.vh
// control states
`define CTL_STATE_IDLE 0
`define CTL_STATE_FETCH0 1
`define CTL_STATE_FETCH1 2
`define CTL_STATE_DEC0 3
`define CTL_STATE_DEC1 4
`define CTL_STATE_EXEC0 5
`define CTL_STATE_EXEC1 6

// opcodes
`define ADD 0
`define SUB 1
`define LSF 2
`define RSF 3
`define AND 4
`define OR 5
`define XOR 6
`define LHI 7
`define LD 8
`define ST 9
`define JLT 16
`define JLE 17
`define JEQ 18
`define JNE 19
`define JIN 20
`define HLT 24

Lab4/ctl.v
`include "defines.vh"
//`include "top.v"
/***********************************
 * CTL module
 **********************************/
module CTL(
	   clk,
	   reset,
	   start,
	   sram_ADDR,
	   sram_DI,
	   sram_EN,
	   sram_WE,
	   sram_DO,
	   opcode,
	   alu0,
	   alu1,
	   aluout_wire
	   );

   // inputs
   input clk;
   input reset;
   input start;
   input [31:0] sram_DO;
   input [31:0] aluout_wire;

   // outputs
   output [15:0] sram_ADDR;
   output [31:0] sram_DI;
   output 	 sram_EN;
   output 	 sram_WE;
   output [31:0] alu0;
   output [31:0] alu1;
   output [4:0]  opcode;

   // registers
   reg [31:0] 	 r2;
   reg [31:0] 	 r3;
   reg [31:0] 	 r4;
   reg [31:0] 	 r5;
   reg [31:0] 	 r6;
   reg [31:0] 	 r7;
   reg [15:0] 	 pc;
   reg [31:0] 	 inst;
   reg [4:0] 	 opcode;
   reg [2:0] 	 dst;
   reg [2:0] 	 src0;
   reg [2:0] 	 src1;
   reg [31:0] 	 alu0;
   reg [31:0] 	 alu1;
   reg [31:0] 	 aluout;
   reg [31:0] 	 immediate;
   reg [31:0] 	 cycle_counter;
   reg [2:0] 	 ctl_state;

   integer 	 verilog_trace_fp, rc;

   initial
     begin
	verilog_trace_fp = $fopen("verilog_trace.txt", "w");
     end

   /***********************************
    * set up sram inputs (outputs from sp)*/

	reg sram_EN;
	reg sram_WE;
	reg[31:0] sram_DI;
	reg[15:0] sram_ADDR;


   // synchronous instructions
   always@(posedge clk) begin
	if (reset) begin
	   // registers reset
	   r2 <= 0;
	   r3 <= 0;
	   r4 <= 0;
	   r5 <= 0;
	   r6 <= 0;
	   r7 <= 0;
	   pc <= 0;
	   inst <= 0;
	   opcode <= 0;
	   dst <= 0;
	   src0 <= 0;
	   src1 <= 0;
	   alu0 <= 0;
	   alu1 <= 0;
	   aluout <= 0;
	   immediate <= 0;
	   cycle_counter <= 0;
	   ctl_state <= 0;
	   
	end else begin
	   // generate cycle trace
	   $fdisplay(verilog_trace_fp, "cycle %0d", cycle_counter);
	   $fdisplay(verilog_trace_fp, "r2 %08x", r2);
	   $fdisplay(verilog_trace_fp, "r3 %08x", r3);
	   $fdisplay(verilog_trace_fp, "r4 %08x", r4);
	   $fdisplay(verilog_trace_fp, "r5 %08x", r5);
	   $fdisplay(verilog_trace_fp, "r6 %08x", r6);
	   $fdisplay(verilog_trace_fp, "r7 %08x", r7);
	   $fdisplay(verilog_trace_fp, "pc %08x", pc);
	   $fdisplay(verilog_trace_fp, "inst %08x", inst);
	   $fdisplay(verilog_trace_fp, "opcode %08x", opcode);
	   $fdisplay(verilog_trace_fp, "dst %08x", dst);
	   $fdisplay(verilog_trace_fp, "src0 %08x", src0);
	   $fdisplay(verilog_trace_fp, "src1 %08x", src1);
	   $fdisplay(verilog_trace_fp, "immediate %08x", immediate);
	   $fdisplay(verilog_trace_fp, "alu0 %08x", alu0);
	   $fdisplay(verilog_trace_fp, "alu1 %08x", alu1);
	   $fdisplay(verilog_trace_fp, "aluout %08x", aluout);
	   $fdisplay(verilog_trace_fp, "cycle_counter %08x", cycle_counter);
	   $fdisplay(verilog_trace_fp, "ctl_state %08x\n", ctl_state);

	   cycle_counter <= cycle_counter + 1;
	   case (ctl_state)

	     	`CTL_STATE_IDLE: begin
                pc <= 0;
                if (start)
                  ctl_state <= `CTL_STATE_FETCH0;
             end

        	`CTL_STATE_FETCH0: begin
			 	ctl_state <= `CTL_STATE_FETCH1;
		 	end

			`CTL_STATE_FETCH1: begin
				inst <= sram_DO; //load the next operation to inst register
				ctl_state <= `CTL_STATE_DEC0;
			end

			`CTL_STATE_DEC0: begin
				//parse opcode to the registers according to specs in lab1
				opcode <= inst[29:25];
				dst <= inst[24:22];
				src0 <= inst[21:19];
				src1 <= inst[18:16];
				//handle immediate
				if(inst[15] == 1) begin// if the immediate is negative
					immediate <= inst|((~(32'b0))<<16); //do sign extension to 32 bits in 2's complement
				end 
				else
					immediate <= inst[15:0];
				ctl_state <= `CTL_STATE_DEC1;
			end

			`CTL_STATE_DEC1: begin
				//load values into alu0
				if(src0==0)
					alu0 <= 0;
				if(src0==1)
					alu0 <= immediate;
				if(src0==2)
					alu0 <= r2;
				if(src0==3)
					alu0 <= r3;
				if(src0==4)
					alu0 <= r4;
				if(src0==5)
					alu0 <= r5;
				if(src0==6)
					alu0 <= r6;
				if(src0==7)
					alu0 <= r7;
				//load value into alu1
				if(src1==0)
					alu1 <= 0;
				if(src1==1)
					alu1 <= immediate;
				if(src1==2)
					alu1 <= r2;
				if(src1==3)
					alu1 <= r3;
				if(src1==4)
					alu1 <= r4;
				if(src1==5)
					alu1 <= r5;
				if(src1==6)
					alu1 <= r6;
				if(src1==7)
					alu1 <= r7;
				ctl_state <= `CTL_STATE_EXEC0;
			end

			`CTL_STATE_EXEC0: begin
				if (opcode!=`LD && opcode!=`ST && opcode!=`HLT) //handle all alu operations
	     			aluout <= aluout_wire;
				else
					
	     		ctl_state <= `CTL_STATE_EXEC1;
			end

			`CTL_STATE_EXEC1: begin
				pc <= pc + 1;
			  	if(opcode == `LD) begin
					if(dst==2)
						r2 <= sram_DO;
					if(dst==3)
						r3 <= sram_DO;	
					if(dst==4)
						r4 <= sram_DO;				  			     		
					if(dst==5)
						r5 <= sram_DO;	
					if(dst==6)
						r6 <= sram_DO;	
					if(dst==7)
						r7 <= sram_DO;	
				end

				else if(opcode == `ST)begin
				  //nothing
				end

				else if(opcode == `HLT) begin
					ctl_state <= `CTL_STATE_IDLE;
					$fclose(verilog_trace_fp);
					$writememh("verilog_sram_out.txt", top.SP.SRAM.mem);
					$finish;
				end

				else if(opcode == `ADD || opcode == `SUB || opcode == `AND || opcode == `OR || opcode == `XOR || opcode == `LSF || opcode == `RSF || opcode == `LHI) begin
					if(dst==2)
						r2 <= aluout_wire;
					if(dst==3)
						r3 <= aluout_wire;
					if(dst==4)
						r4 <= aluout_wire;
					if(dst==5)
						r5 <= aluout_wire;	
					if(dst==6)
						r6 <= aluout_wire;	
					if(dst==7)
						r7 <= aluout_wire;	
				end

				else if(opcode == `JEQ || opcode == `JLE || opcode == `JNE || opcode == `JIN) begin //handle jump
					if(aluout == 1) begin
					  r7 <= pc; //store old pc
					  pc <= immediate;
					end
				end	

				ctl_state <= `CTL_STATE_FETCH0;
			end
	   endcase
	end // !reset
end // @posedge(clk)

	//handle sram inputs for every state switch
	always @(ctl_state) begin

		sram_EN = 1;
		sram_WE = 0;
		sram_ADDR = 0;
		sram_DI = 0;

		case(ctl_state)

			`CTL_STATE_FETCH0: begin
				sram_EN = 1;
				sram_WE = 0;
				sram_ADDR = pc[15:0];
				sram_DI = 0;
			end

			`CTL_STATE_EXEC0: begin
				if (opcode == `LD) begin //handle load operation
					sram_EN = 1;
					sram_WE = 0;
					sram_ADDR = alu1[15:0];
					sram_DI = 0;
				end
			end

			`CTL_STATE_EXEC1: begin
				if (opcode == `ST) begin //handle store operation
					sram_EN = 1;
					sram_WE = 1;
					sram_ADDR = alu1[15:0];
					sram_DI = alu0;
				end
			end

			default: begin
				sram_EN = 0;
				sram_WE = 0;
				sram_ADDR = 0;
				sram_DI = 0;
			end
		endcase
	end
		



endmodule // CTL

Lab4/alu.v
`include "defines.vh"

/***********************************
 * ALU module
 **********************************/
module ALU(opcode, alu0, alu1, aluout);
   
   input [4:0] opcode;
   input [31:0] alu0, alu1;
   output [31:0] aluout;
   reg [31:0] 	 aluout;

   always@(alu0 or alu1 or opcode)
     begin
	case (opcode)
	  `ADD: aluout = alu0 + alu1;
	  /***********************************
           * TODO: fill here
           **********************************/

	endcase
     end
endmodule // alu

Lab4/sp.v

/***********************************
 * SP module
 **********************************/

 `include "alu.v"
 `include "ctl.v"
 `include "sram.v"

module SP(clk, reset, start);
   input clk;
   input reset;
   input start;

   wire [15:0] sram_ADDR;
   wire [31:0] sram_DI;
   wire        sram_EN;
   wire        sram_WE;
   wire [31:0] sram_DO;
   wire [4:0]  opcode;
   wire [31:0] alu0;
   wire [31:0] alu1;
   wire [31:0] aluout_wire;

   // instantiate ALU, CTL and SRAM modules
   ALU ALU(opcode, alu0, alu1, aluout);
   CTL CTL(clk, reset, start, sram_ADDR, sram_DI, sram_EN, sram_WE, sram_DO, opcode, alu0, alu1, aluout_wire);
   SRAM SRAM(clk, sram_ADDR, sram_DI, sram_EN, sram_WE, sram_DO);
endmodule

Lab4/top.v
/***********************************
 * TOP module
 **********************************/
 `include "sp.v"
 
module top;

   reg clk, reset, start;

   SP SP(clk, reset, start);

   always #5 clk = ~clk;
   
   initial
     begin
	$readmemh("example.bin", top.SP.SRAM.mem);
	clk = 1;     
	reset = 1;
	start = 0;
	$dumpfile("waves.vcd");
	$dumpvars;
	#100;
	reset = 0;
	start = 1;
     end
endmodule // top

Lab4/mult test/waves.vcd
$date
    Nov 28, 2021  18:36:18
$end
$version
    TOOL:	ncsim(64)	15.20-s085
$end
$timescale
    1 ns
$end

$scope module top $end
$var reg       1 !    clk  $end
$var reg       1 "    reset  $end
$var reg       1 #    start  $end

$scope module SP $end
$var wire      1 $    clk  $end
$var wire      1 %    reset  $end
$var wire      1 &    start  $end
$var wire     16 '    sram_ADDR [15:0] $end
$var wire     32 (    sram_DI [31:0] $end
$var wire      1 )    sram_EN  $end
$var wire      1 *    sram_WE  $end
$var wire     32 +    sram_DO [31:0] $end
$var wire      5 ,    opcode [4:0] $end
$var wire     32 -    alu0 [31:0] $end
$var wire     32 .    alu1 [31:0] $end
$var wire     32 /    aluout_wire [31:0] $end

$scope module ALU $end
$var wire      5 ,    opcode [4:0] $end
$var wire     32 -    alu0 [31:0] $end
$var wire     32 .    alu1 [31:0] $end
$var reg      32 0    aluout [31:0] $end
$upscope $end


$scope module CTL $end
$var wire      1 $    clk  $end
$var wire      1 %    reset  $end
$var wire      1 &    start  $end
$var wire     32 +    sram_DO [31:0] $end
$var wire     32 /    aluout_wire [31:0] $end
$var reg      16 1    sram_ADDR [15:0] $end
$var reg      32 2    sram_DI [31:0] $end
$var reg       1 3    sram_EN  $end
$var reg       1 4    sram_WE  $end
$var reg      32 5    alu0 [31:0] $end
$var reg      32 6    alu1 [31:0] $end
$var reg       5 7    opcode [4:0] $end
$var reg      32 8    r2 [31:0] $end
$var reg      32 9    r3 [31:0] $end
$var reg      32 :    r4 [31:0] $end
$var reg      32 ;    r5 [31:0] $end
$var reg      32 <    r6 [31:0] $end
$var reg      32 =    r7 [31:0] $end
$var reg      16 >    pc [15:0] $end
$var reg      32 ?    inst [31:0] $end
$var reg       3 @    dst [2:0] $end
$var reg       3 A    src0 [2:0] $end
$var reg       3 B    src1 [2:0] $end
$var reg      32 C    aluout [31:0] $end
$var reg      32 D    immediate [31:0] $end
$var reg      32 E    cycle_counter [31:0] $end
$var reg       3 F    ctl_state [2:0] $end
$var integer  32 G    verilog_trace_fp  $end
$var integer  32 H    rc  $end
$upscope $end


$scope module SRAM $end
$var wire      1 $    clk  $end
$var wire     16 '    addr [15:0] $end
$var wire     32 (    di [31:0] $end
$var wire      1 )    en  $end
$var wire      1 *    we  $end
$var reg      32 I    do [31:0] $end
$upscope $end

$upscope $end

$upscope $end

$enddefinitions $end
$dumpvars
1!
1"
0#
1$
1%
0&
b0 '
b0 (
0)
0*
bx +
b0 ,
b0 -
b0 .
b0 /
b0 0
b0 1
b0 2
03
04
b0 5
b0 6
b0 7
b0 8
b0 9
b0 :
b0 ;
b0 <
b0 =
b0 >
b0 ?
b0 @
b0 A
b0 B
b0 C
b0 D
b0 E
b0 F
b10000000000000000000000000000011 G
bx H
bx I
$end
#5
0!
0$
#10
1!
1$
#15
0!
0$
#20
1!
1$
#25
0!
0$
#30
1!
1$
#35
0!
0$
#40
1!
1$
#45
0!
0$
#50
1!
1$
#55
0!
0$
#60
1!
1$
#65
0!
0$
#70
1!
1$
#75
0!
0$
#80
1!
1$
#85
0!
0$
#90
1!
1$
#95
0!
0$
#100
0"
1#
1!
1$
1&
0%
b1 E
b1 F
13
1)
#105
0!
0$
#110
1!
1$
b10000100000010000001111101000 I
b10 E
b10 F
03
0)
b10000100000010000001111101000 +
#115
0!
0$
#120
1!
1$
b11 E
b10000100000010000001111101000 ?
b11 F
13
03
#125
0!
0$
#130
1!
1$
b100 E
b1000 7
b10 @
b1 B
b1111101000 D
b100 F
13
03
b1000 ,
#135
0!
0$
#140
1!
1$
b101 E
b1111101000 6
b101 F
13
b1111101000 1
b1111101000 '
1)
b1111101000 .
#145
0!
0$
#150
1!
1$
b100 I
b110 E
b110 F
b0 1
b0 '
b100 +
#155
0!
0$
#160
1!
1$
b10000100000010000001111101000 I
b111 E
b1 >
b100 8
b1 F
b1 1
b1 '
b10000100000010000001111101000 +
#165
0!
0$
#170
1!
1$
b10000110000010000001111101001 I
b1000 E
b10 F
b0 1
03
0)
b0 '
b10000110000010000001111101001 +
#175
0!
0$
#180
1!
1$
b1001 E
b10000110000010000001111101001 ?
b11 F
13
03
#185
0!
0$
#190
1!
1$
b1010 E
b11 @
b1111101001 D
b100 F
13
03
#195
0!
0$
#200
1!
1$
b1011 E
b1111101001 6
b101 F
13
b1111101001 1
b1111101001 '
1)
b1111101001 .
#205
0!
0$
#210
1!
1$
b11111111111111111111111111111100 I
b1100 E
b110 F
b0 1
b0 '
b11111111111111111111111111111100 +
#215
0!
0$
#220
1!
1$
b10000100000010000001111101000 I
b1101 E
b10 >
b11111111111111111111111111111100 9
b1 F
b10 1
b10 '
b10000100000010000001111101000 +
#225
0!
0$
#230
1!
1$
b1000000010000000000000001 I
b1110 E
b10 F
b0 1
03
0)
b0 '
b1000000010000000000000001 +
#235
0!
0$
#240
1!
1$
b1111 E
b1000000010000000000000001 ?
b11 F
13
03
#245
0!
0$
#250
1!
1$
b10000 E
b0 7
b100 @
b1 D
b100 F
13
03
b0 ,
b1111101001 0
b1111101001 /
#255
0!
0$
#260
1!
1$
b10001 E
b1 6
b101 F
13
1)
b1 .
b1 0
b1 /
#265
0!
0$
#270
1!
1$
b10000100000010000001111101000 I
b10010 E
b1 C
b110 F
b10000100000010000001111101000 +
#275
0!
0$
#280
1!
1$
b10011 E
b11 >
b1 :
b1 F
b11 1
b11 '
#285
0!
0$
#290
1!
1$
b1100000000000000000000000 I
b10100 E
b10 F
b0 1
03
0)
b0 '
b1100000000000000000000000 +
#295
0!
0$
#300
1!
1$
b10101 E
b1100000000000000000000000 ?
b11 F
13
03
#305
0!
0$
#310
1!
1$
b10110 E
b110 @
b0 B
b0 D
b100 F
13
03
#315
0!
0$
#320
1!
1$
b10111 E
b0 6
b101 F
13
1)
b0 .
b0 0
b0 /
#325
0!
0$
#330
1!
1$
b10000100000010000001111101000 I
b11000 E
b0 C
b110 F
b10000100000010000001111101000 +
#335
0!
0$
#340
1!
1$
b11001 E
b100 >
b1 F
b100 1
b100 '
#345
0!
0$
#350
1!
1$
b1001011000110000000000000000 I
b11010 E
b10 F
b0 1
03
0)
b0 '
b1001011000110000000000000000 +
#355
0!
0$
#360
1!
1$
b11011 E
b1001011000110000000000000000 ?
b11 F
13
03
#365
0!
0$
#370
1!
1$
b11100 E
b100 7
b101 @
b100 A
b11 B
b100 F
13
03
b100 ,
#375
0!
0$
#380
1!
1$
b11101 E
b1 5
b11111111111111111111111111111100 6
b101 F
13
1)
b11111111111111111111111111111100 .
b1 -
#385
0!
0$
#390
1!
1$
b10000100000010000001111101000 I
b11110 E
b110 F
b10000100000010000001111101000 +
#395
0!
0$
#400
1!
1$
b11111 E
b101 >
b1 F
b101 1
b101 '
#405
0!
0$
#410
1!
1$
b100100001010000000000000000111 I
b100000 E
b10 F
b0 1
03
0)
b0 '
b100100001010000000000000000111 +
#415
0!
0$
#420
1!
1$
b100001 E
b100100001010000000000000000111 ?
b11 F
13
03
#425
0!
0$
#430
1!
1$
b100010 E
b10010 7
b0 @
b101 A
b0 B
b111 D
b100 F
13
03
b10010 ,
#435
0!
0$
#440
1!
1$
b100011 E
b0 5
b0 6
b101 F
13
1)
b0 .
b0 -
b1 0
b1 /
#445
0!
0$
#450
1!
1$
b10000100000010000001111101000 I
b100100 E
b1 C
b110 F
b10000100000010000001111101000 +
#455
0!
0$
#460
1!
1$
b100101 E
b110 >
b101 =
b111 >
b1 F
b111 1
b111 '
#465
0!
0$
#470
1!
1$
b101001000010000000000000001 I
b100110 E
b10 F
b0 1
03
0)
b0 '
b101001000010000000000000001 +
#475
0!
0$
#480
1!
1$
b100111 E
b101001000010000000000000001 ?
b11 F
13
03
#485
0!
0$
#490
1!
1$
b101000 E
b10 7
b100 @
b100 A
b1 B
b1 D
b100 F
13
03
b10 ,
b0 0
b0 /
#495
0!
0$
#500
1!
1$
b101001 E
b1 5
b1 6
b101 F
13
1)
b1 .
b1 -
b10 0
b10 /
#505
0!
0$
#510
1!
1$
b10000100000010000001111101000 I
b101010 E
b10 C
b110 F
b10000100000010000001111101000 +
#515
0!
0$
#520
1!
1$
b101011 E
b1000 >
b10 :
b1 F
b1000 1
b1000 '
#525
0!
0$
#530
1!
1$
b100100100010000000000000001 I
b101100 E
b10 F
b0 1
03
0)
b0 '
b100100100010000000000000001 +
#535
0!
0$
#540
1!
1$
b101101 E
b100100100010000000000000001 ?
b11 F
13
03
#545
0!
0$
#550
1!
1$
b101110 E
b10 @
b10 A
b100 F
13
03
#555
0!
0$
#560
1!
1$
b101111 E
b100 5
b101 F
13
1)
b100 -
b1000 0
b1000 /
#565
0!
0$
#570
1!
1$
b10000100000010000001111101000 I
b110000 E
b1000 C
b110 F
b10000100000010000001111101000 +
#575
0!
0$
#580
1!
1$
b110001 E
b1001 >
b1000 8
b1 F
b1001 1
b1001 '
#585
0!
0$
#590
1!
1$
b100000000001000000000000000100 I
b110010 E
b10 F
b0 1
03
0)
b0 '
b100000000001000000000000000100 +
#595
0!
0$
#600
1!
1$
b110011 E
b100000000001000000000000000100 ?
b11 F
13
03
#605
0!
0$
#610
1!
1$
b110100 E
b10000 7
b0 @
b0 A
b100 B
b100 D
b100 F
13
03
b10000 ,
b0 0
b0 /
#615
0!
0$
#620
1!
1$
b110101 E
b0 5
b10 6
b101 F
13
1)
b10 .
b0 -
b1 0
b1 /
#625
0!
0$
#630
1!
1$
b10000100000010000001111101000 I
b110110 E
b1 C
b110 F
b10000100000010000001111101000 +
#635
0!
0$
#640
1!
1$
b110111 E
b1010 >
b1001 =
b100 >
b1 F
b100 1
b100 '
#645
0!
0$
#650
1!
1$
b1001011000110000000000000000 I
b111000 E
b10 F
b0 1
03
0)
b0 '
b1001011000110000000000000000 +
#655
0!
0$
#660
1!
1$
b111001 E
b1001011000110000000000000000 ?
b11 F
13
03
#665
0!
0$
#670
1!
1$
b111010 E
b100 7
b101 @
b100 A
b11 B
b0 D
b100 F
13
03
b100 ,
b0 0
b0 /
#675
0!
0$
#680
1!
1$
b111011 E
b10 5
b11111111111111111111111111111100 6
b101 F
13
1)
b11111111111111111111111111111100 .
b10 -
#685
0!
0$
#690
1!
1$
b10000100000010000001111101000 I
b111100 E
b0 C
b110 F
b10000100000010000001111101000 +
#695
0!
0$
#700
1!
1$
b111101 E
b101 >
b1 F
b101 1
b101 '
#705
0!
0$
#710
1!
1$
b100100001010000000000000000111 I
b111110 E
b10 F
b0 1
03
0)
b0 '
b100100001010000000000000000111 +
#715
0!
0$
#720
1!
1$
b111111 E
b100100001010000000000000000111 ?
b11 F
13
03
#725
0!
0$
#730
1!
1$
b1000000 E
b10010 7
b0 @
b101 A
b0 B
b111 D
b100 F
13
03
b10010 ,
#735
0!
0$
#740
1!
1$
b1000001 E
b0 5
b0 6
b101 F
13
1)
b0 .
b0 -
b1 0
b1 /
#745
0!
0$
#750
1!
1$
b10000100000010000001111101000 I
b1000010 E
b1 C
b110 F
b10000100000010000001111101000 +
#755
0!
0$
#760
1!
1$
b1000011 E
b110 >
b101 =
b111 >
b1 F
b111 1
b111 '
#765
0!
0$
#770
1!
1$
b101001000010000000000000001 I
b1000100 E
b10 F
b0 1
03
0)
b0 '
b101001000010000000000000001 +
#775
0!
0$
#780
1!
1$
b1000101 E
b101001000010000000000000001 ?
b11 F
13
03
#785
0!
0$
#790
1!
1$
b1000110 E
b10 7
b100 @
b100 A
b1 B
b1 D
b100 F
13
03
b10 ,
b0 0
b0 /
#795
0!
0$
#800
1!
1$
b1000111 E
b10 5
b1 6
b101 F
13
1)
b1 .
b10 -
b100 0
b100 /
#805
0!
0$
#810
1!
1$
b10000100000010000001111101000 I
b1001000 E
b100 C
b110 F
b10000100000010000001111101000 +
#815
0!
0$
#820
1!
1$
b1001001 E
b1000 >
b100 :
b1 F
b1000 1
b1000 '
#825
0!
0$
#830
1!
1$
b100100100010000000000000001 I
b1001010 E
b10 F
b0 1
03
0)
b0 '
b100100100010000000000000001 +
#835
0!
0$
#840
1!
1$
b1001011 E
b100100100010000000000000001 ?
b11 F
13
03
#845
0!
0$
#850
1!
1$
b1001100 E
b10 @
b10 A
b100 F
13
03
#855
0!
0$
#860
1!
1$
b1001101 E
b1000 5
b101 F
13
1)
b1000 -
b10000 0
b10000 /
#865
0!
0$
#870
1!
1$
b10000100000010000001111101000 I
b1001110 E
b10000 C
b110 F
b10000100000010000001111101000 +
#875
0!
0$
#880
1!
1$
b1001111 E
b1001 >
b10000 8
b1 F
b1001 1
b1001 '
#885
0!
0$
#890
1!
1$
b100000000001000000000000000100 I
b1010000 E
b10 F
b0 1
03
0)
b0 '
b100000000001000000000000000100 +
#895
0!
0$
#900
1!
1$
b1010001 E
b100000000001000000000000000100 ?
b11 F
13
03
#905
0!
0$
#910
1!
1$
b1010010 E
b10000 7
b0 @
b0 A
b100 B
b100 D
b100 F
13
03
b10000 ,
b0 0
b0 /
#915
0!
0$
#920
1!
1$
b1010011 E
b0 5
b100 6
b101 F
13
1)
b100 .
b0 -
b1 0
b1 /
#925
0!
0$
#930
1!
1$
b10000100000010000001111101000 I
b1010100 E
b1 C
b110 F
b10000100000010000001111101000 +
#935
0!
0$
#940
1!
1$
b1010101 E
b1010 >
b1001 =
b100 >
b1 F
b100 1
b100 '
#945
0!
0$
#950
1!
1$
b1001011000110000000000000000 I
b1010110 E
b10 F
b0 1
03
0)
b0 '
b1001011000110000000000000000 +
#955
0!
0$
#960
1!
1$
b1010111 E
b1001011000110000000000000000 ?
b11 F
13
03
#965
0!
0$
#970
1!
1$
b1011000 E
b100 7
b101 @
b100 A
b11 B
b0 D
b100 F
13
03
b100 ,
b0 0
b0 /
#975
0!
0$
#980
1!
1$
b1011001 E
b100 5
b11111111111111111111111111111100 6
b101 F
13
1)
b11111111111111111111111111111100 .
b100 -
b100 0
b100 /
#985
0!
0$
#990
1!
1$
b10000100000010000001111101000 I
b1011010 E
b100 C
b110 F
b10000100000010000001111101000 +
#995
0!
0$
#1000
1!
1$
b1011011 E
b101 >
b100 ;
b1 F
b101 1
b101 '
#1005
0!
0$
#1010
1!
1$
b100100001010000000000000000111 I
b1011100 E
b10 F
b0 1
03
0)
b0 '
b100100001010000000000000000111 +
#1015
0!
0$
#1020
1!
1$
b1011101 E
b100100001010000000000000000111 ?
b11 F
13
03
#1025
0!
0$
#1030
1!
1$
b1011110 E
b10010 7
b0 @
b101 A
b0 B
b111 D
b100 F
13
03
b10010 ,
b0 0
b0 /
#1035
0!
0$
#1040
1!
1$
b1011111 E
b0 6
b101 F
13
1)
b0 .
#1045
0!
0$
#1050
1!
1$
b10000100000010000001111101000 I
b1100000 E
b0 C
b110 F
b10000100000010000001111101000 +
#1055
0!
0$
#1060
1!
1$
b1100001 E
b110 >
b1 F
b110 1
b110 '
#1065
0!
0$
#1070
1!
1$
b1101100100000000000000000 I
b1100010 E
b10 F
b0 1
03
0)
b0 '
b1101100100000000000000000 +
#1075
0!
0$
#1080
1!
1$
b1100011 E
b1101100100000000000000000 ?
b11 F
13
03
#1085
0!
0$
#1090
1!
1$
b1100100 E
b0 7
b110 @
b110 A
b10 B
b0 D
b100 F
13
03
b0 ,
b100 0
b100 /
#1095
0!
0$
#1100
1!
1$
b1100101 E
b0 5
b10000 6
b101 F
13
1)
b10000 .
b0 -
b10000 0
b10000 /
#1105
0!
0$
#1110
1!
1$
b10000100000010000001111101000 I
b1100110 E
b10000 C
b110 F
b10000100000010000001111101000 +
#1115
0!
0$
#1120
1!
1$
b1100111 E
b111 >
b10000 <
b1 F
b111 1
b111 '
#1125
0!
0$
#1130
1!
1$
b101001000010000000000000001 I
b1101000 E
b10 F
b0 1
03
0)
b0 '
b101001000010000000000000001 +
#1135
0!
0$
#1140
1!
1$
b1101001 E
b101001000010000000000000001 ?
b11 F
13
03
#1145
0!
0$
#1150
1!
1$
b1101010 E
b10 7
b100 @
b100 A
b1 B
b1 D
b100 F
13
03
b10 ,
b0 0
b0 /
#1155
0!
0$
#1160
1!
1$
b1101011 E
b100 5
b1 6
b101 F
13
1)
b1 .
b100 -
b1000 0
b1000 /
#1165
0!
0$
#1170
1!
1$
b10000100000010000001111101000 I
b1101100 E
b1000 C
b110 F
b10000100000010000001111101000 +
#1175
0!
0$
#1180
1!
1$
b1101101 E
b1000 >
b1000 :
b1 F
b1000 1
b1000 '
#1185
0!
0$
#1190
1!
1$
b100100100010000000000000001 I
b1101110 E
b10 F
b0 1
03
0)
b0 '
b100100100010000000000000001 +
#1195
0!
0$
#1200
1!
1$
b1101111 E
b100100100010000000000000001 ?
b11 F
13
03
#1205
0!
0$
#1210
1!
1$
b1110000 E
b10 @
b10 A
b100 F
13
03
#1215
0!
0$
#1220
1!
1$
b1110001 E
b10000 5
b101 F
13
1)
b10000 -
b100000 0
b100000 /
#1225
0!
0$
#1230
1!
1$
b10000100000010000001111101000 I
b1110010 E
b100000 C
b110 F
b10000100000010000001111101000 +
#1235
0!
0$
#1240
1!
1$
b1110011 E
b1001 >
b100000 8
b1 F
b1001 1
b1001 '
#1245
0!
0$
#1250
1!
1$
b100000000001000000000000000100 I
b1110100 E
b10 F
b0 1
03
0)
b0 '
b100000000001000000000000000100 +
#1255
0!
0$
#1260
1!
1$
b1110101 E
b100000000001000000000000000100 ?
b11 F
13
03
#1265
0!
0$
#1270
1!
1$
b1110110 E
b10000 7
b0 @
b0 A
b100 B
b100 D
b100 F
13
03
b10000 ,
b0 0
b0 /
#1275
0!
0$
#1280
1!
1$
b1110111 E
b0 5
b1000 6
b101 F
13
1)
b1000 .
b0 -
b1 0
b1 /
#1285
0!
0$
#1290
1!
1$
b10000100000010000001111101000 I
b1111000 E
b1 C
b110 F
b10000100000010000001111101000 +
#1295
0!
0$
#1300
1!
1$
b1111001 E
b1010 >
b100 >
b1 F
b100 1
b100 '
#1305
0!
0$
#1310
1!
1$
b1001011000110000000000000000 I
b1111010 E
b10 F
b0 1
03
0)
b0 '
b1001011000110000000000000000 +
#1315
0!
0$
#1320
1!
1$
b1111011 E
b1001011000110000000000000000 ?
b11 F
13
03
#1325
0!
0$
#1330
1!
1$
b1111100 E
b100 7
b101 @
b100 A
b11 B
b0 D
b100 F
13
03
b100 ,
b0 0
b0 /
#1335
0!
0$
#1340
1!
1$
b1111101 E
b1000 5
b11111111111111111111111111111100 6
b101 F
13
1)
b11111111111111111111111111111100 .
b1000 -
b1000 0
b1000 /
#1345
0!
0$
#1350
1!
1$
b10000100000010000001111101000 I
b1111110 E
b1000 C
b110 F
b10000100000010000001111101000 +
#1355
0!
0$
#1360
1!
1$
b1111111 E
b101 >
b1000 ;
b1 F
b101 1
b101 '
#1365
0!
0$
#1370
1!
1$
b100100001010000000000000000111 I
b10000000 E
b10 F
b0 1
03
0)
b0 '
b100100001010000000000000000111 +
#1375
0!
0$
#1380
1!
1$
b10000001 E
b100100001010000000000000000111 ?
b11 F
13
03
#1385
0!
0$
#1390
1!
1$
b10000010 E
b10010 7
b0 @
b101 A
b0 B
b111 D
b100 F
13
03
b10010 ,
b0 0
b0 /
#1395
0!
0$
#1400
1!
1$
b10000011 E
b0 6
b101 F
13
1)
b0 .
#1405
0!
0$
#1410
1!
1$
b10000100000010000001111101000 I
b10000100 E
b0 C
b110 F
b10000100000010000001111101000 +
#1415
0!
0$
#1420
1!
1$
b10000101 E
b110 >
b1 F
b110 1
b110 '
#1425
0!
0$
#1430
1!
1$
b1101100100000000000000000 I
b10000110 E
b10 F
b0 1
03
0)
b0 '
b1101100100000000000000000 +
#1435
0!
0$
#1440
1!
1$
b10000111 E
b1101100100000000000000000 ?
b11 F
13
03
#1445
0!
0$
