Lab3/ex8/fifo.v
module fifo(clk, reset, in, push, pop, out, full);
   parameter N=4; // determines the maximum number of words in queue.
   parameter M=2; // determines the bit-width of each word, stored in the queue.

   input clk, reset, push, pop;
   input [M-1:0] in;
   output [M-1:0] out;
   output full;

   // Fill Here

   integer        n = 0 ;
   reg            full_fifo = 0 ;
   reg [N*M-1:0]  fifo = 0;
   reg [M-1:0]    word ;

   always @(posedge clk or reset) begin
      if(reset) begin   //reset everything to make sure 
         n <= 0 ;
         fifo <= 0 ;
         word <= 0 ;
         full_fifo <= 0; 
      end
      else begin
         
         if ( n == 0) begin //fifo is empty 
            if ( push == 1) begin
               n <= 1 ;
               word <= in ; 
               fifo <= (in << M*(N-1)) | fifo ; 
            end
            else begin 
               if(~push) 
                  word <= 2'd0 ; 
            end
         end

         else begin // n != 0 

            if( n >= N) begin //should never be n>N but only to make sure 
               if(push == 1 && pop == 1) begin
                  word <= fifo;
                  fifo <= ( in << M*(N-1)) | (fifo >>> M );
               end else; 

               if (push == 0 && pop == 1) begin
                  n <= n -1 ;
                  full_fifo <= 0 ; 
                  word <= fifo ; 
                  fifo <= ((fifo >>> M) <<< M) ; 
               end else ;
            end 

            else begin // 0 < n < N case 
               if(push == 1 && pop == 1) begin
                  word <= (fifo >>> M*(N-n));
                  fifo <= ( in << M*(N-1)) | (((fifo >>> M*(N-n+1)) <<< M*(N-n+1)) >>> M);
               end else;

               if( push ==1 && pop == 0) begin 
                  word <= (fifo >>> M*(N-n));
                  fifo <= (in << (M*(N-1))) | fifo >>> M ;
                  n <= n + 1 ; 
                  if( n == N - 1 )
                     full_fifo <= 1 ;
               end else ;

               if( push ==0 && pop == 1 ) begin 
                  word <= (fifo >>> M*(N-n)) ;
						fifo <= ((fifo >>> M*(N-n+1)) <<< M*(N-n+1));
						n <= n - 1;
					end else;
            
            end
         end

      end
   end 
   assign out = word;
   assign full = full_fifo;


endmodule

Lab3/ex8/fifo_tb.v
`include "fifo.v"

module main;
   reg clk, reset, push, pop;
   reg [1:0] in;
   wire [1:0] out;
   wire full;
   integer failure = 0;

   // Correct the parameter assignment
   fifo #(4,2) f (clk, reset, in, push, pop, out, full);

   always #5 clk = ~clk;

   // Fill Here

   initial begin
      $dumpfile("waves.vcd");
      $dumpvars;
      clk = 0 ;
      #10

      //init - check the reset 
      reset = 1;
      in = 0;
      push = 0;
      pop = 0; 
      #10
      if (full != 0 || out != 0) 
         failure <= 1;

      #10 
      reset =0;
      #10 
      
      // push 1
      push = 1;
      in = 2'd1;
      #10;
      push=0;
      #10
      if (full != 0 || out != 2'd1 )
         failure <= 2;

      //push 2
      #10;
      push =1;
      in = 2'd2;
      #10;
      push=0;
      #10
      if (full != 0 || out != 2'd1)
         failure <= 3;

      // push 3
      #10;
      push =1;
      in = 2'd3;
      #10;
      push=0;
      #10
      if (full != 0 || out != 2'd1 )
         failure <= 4;

      // push 3
      #10;
      push =1;
      in = 2'd3;
      #10;
      push=0;
      #10
      if (full != 1 || out != 2'd1 ) 
         failure <= 5;

      //push when full - should do nothing 
      #10;
      push =1;
      in = 2'd3;
      #10;
      push=0;
      #10
      if (full != 1 || out != 2'd1 )
         failure <= 6;

      // pop (1)
      #10;
      pop =1;
      in = 0;
      #10;
      pop=0;
      #10
      if (full != 0 || out != 2'd1 ) 
         failure <= 7;

      // pop (2)
      #10;
      pop =1;
      #10;
      pop=0;
      #10
      if (full != 0 || out != 2'd2 )
         failure <= 8;

      // pop (3) & push (2)
      #10;
      pop =1;
      push = 1;
      in = 2'd2;
      #10;
      pop=0;
      push=0;
      #10
      if (full != 0 || out != 2'd3 ) 
         failure <= 9;

      #10 
      if(failure == 0)
         $display("PASSED ALL TESTS");
      else
         $display("DID NOT PASS ALL TESTS. last failureed in %d:", failure);

      $finish;
   end

endmodule

Lab3/ex8/waves.vcd
$date
	Fri Nov 19 15:41:18 2021
$end
$version
	Icarus Verilog
$end
$timescale
	1s
$end
$scope module main $end
$var wire 2 ! out [1:0] $end
$var wire 1 " full $end
$var reg 1 # clk $end
$var reg 2 $ in [1:0] $end
$var reg 1 % pop $end
$var reg 1 & push $end
$var reg 1 ' reset $end
$var integer 32 ( failure [31:0] $end
$scope module f $end
$var wire 1 # clk $end
$var wire 1 " full $end
$var wire 2 ) in [1:0] $end
$var wire 2 * out [1:0] $end
$var wire 1 % pop $end
$var wire 1 & push $end
$var wire 1 ' reset $end
$var reg 8 + fifo [7:0] $end
$var reg 1 , full_fifo $end
$var reg 2 - word [1:0] $end
$var integer 32 . n [31:0] $end
$upscope $end
$upscope $end
$enddefinitions $end
#0
$dumpvars
b0 .
bx -
0,
b0 +
bx *
bx )
b0 (
x'
x&
x%
bx $
0#
0"
bx !
$end
#5
1#
#10
b0 !
b0 *
b0 -
0#
0%
0&
b0 $
b0 )
1'
#15
1#
#20
0#
#25
1#
#30
0#
0'
#35
1#
#40
0#
b1 $
b1 )
1&
#45
b1000000 +
b1 !
b1 *
b1 -
b1 .
1#
#50
0#
0&
#55
1#
#60
0#
#65
1#
#70
0#
b10 $
b10 )
1&
#75
b10 .
b10010000 +
1#
#80
0#
0&
#85
1#
#90
0#
#95
1#
#100
0#
b11 $
b11 )
1&
#105
b11 .
b11100100 +
1#
#110
0#
0&
#115
1#
#120
0#
#125
1#
#130
0#
1&
#135
1"
1,
b100 .
b11111001 +
1#
#140
0#
0&
#145
1#
#150
0#
#155
1#
#160
0#
1&
#165
1#
#170
0#
0&
#175
1#
#180
0#
#185
1#
#190
0#
b0 $
b0 )
1%
#195
b11111000 +
0"
0,
b11 .
1#
#200
0#
0%
#205
1#
#210
0#
#215
1#
#220
0#
1%
#225
b10 .
b11110000 +
b10 !
b10 *
b10 -
1#
#230
0#
0%
#235
1#
#240
0#
#245
1#
#250
0#
b10 $
b10 )
1&
1%
#255
b10110000 +
b11 !
b11 *
b11 -
1#
#260
0#
0&
0%
